c14n/Canonicalize.py
c14n/NumberToJson.py
c14n/__init__.py
pyld/__about__.py
pyld/__init__.py
pyld/context_resolver.py
pyld/jsonld.py
pyld/resolved_context.py
pyld/documentloader/__init__.py
pyld/documentloader/aiohttp.py
pyld/documentloader/requests.py
PyLD-2.0.4.dist-info/LICENSE
PyLD-2.0.4.dist-info/METADATA
PyLD-2.0.4.dist-info/WHEEL
PyLD-2.0.4.dist-info/top_level.txt
PyLD-2.0.4.dist-info/RECORD
